djangocms_page_sitemap/__init__.py
djangocms_page_sitemap/admin.py
djangocms_page_sitemap/cms_toolbars.py
djangocms_page_sitemap/models.py
djangocms_page_sitemap/settings.py
djangocms_page_sitemap/sitemap.py
djangocms_page_sitemap/sitemap_urls.py
djangocms_page_sitemap/utils.py
djangocms_page_sitemap/locale/ar/LC_MESSAGES/django.mo
djangocms_page_sitemap/locale/ar/LC_MESSAGES/django.po
djangocms_page_sitemap/locale/de/LC_MESSAGES/django.mo
djangocms_page_sitemap/locale/de/LC_MESSAGES/django.po
djangocms_page_sitemap/locale/en/LC_MESSAGES/django.mo
djangocms_page_sitemap/locale/en/LC_MESSAGES/django.po
djangocms_page_sitemap/locale/es/LC_MESSAGES/django.mo
djangocms_page_sitemap/locale/es/LC_MESSAGES/django.po
djangocms_page_sitemap/locale/it/LC_MESSAGES/django.mo
djangocms_page_sitemap/locale/it/LC_MESSAGES/django.po
djangocms_page_sitemap/locale/lt/LC_MESSAGES/django.mo
djangocms_page_sitemap/locale/lt/LC_MESSAGES/django.po
djangocms_page_sitemap/locale/pt_BR/LC_MESSAGES/django.mo
djangocms_page_sitemap/locale/pt_BR/LC_MESSAGES/django.po
djangocms_page_sitemap/locale/ru/LC_MESSAGES/django.mo
djangocms_page_sitemap/locale/ru/LC_MESSAGES/django.po
djangocms_page_sitemap/locale/tr/LC_MESSAGES/django.mo
djangocms_page_sitemap/locale/tr/LC_MESSAGES/django.po
djangocms_page_sitemap/migrations/0001_initial.py
djangocms_page_sitemap/migrations/0002_auto_20151018_1451.py
djangocms_page_sitemap/migrations/0003_auto_20151018_1612.py
djangocms_page_sitemap/migrations/0004_auto_20180202_1044.py
djangocms_page_sitemap/migrations/0005_auto_20180324_1050.py
djangocms_page_sitemap/migrations/__init__.py
djangocms_page_sitemap/templatetags/__init__.py
djangocms_page_sitemap/templatetags/robots_index.py
djangocms_page_sitemap-1.4.0.dist-info/LICENSE
djangocms_page_sitemap-1.4.0.dist-info/METADATA
djangocms_page_sitemap-1.4.0.dist-info/WHEEL
djangocms_page_sitemap-1.4.0.dist-info/top_level.txt
djangocms_page_sitemap-1.4.0.dist-info/RECORD
