Metadata-Version: 2.2
Name: djangocms-page-sitemap
Version: 1.4.0
Summary: django CMS page extension to handle sitemap customization
Home-page: https://github.com/nephila/djangocms-page-sitemap
Author: Iacopo Spalletti
Author-email: i.spalletti@nephila.digital
License: BSD
Project-URL: Documentation, https://djangocms-page-sitemap.readthedocs.io/
Keywords: django cms,sitemap,django-app-enabler addon
Classifier: Development Status :: 5 - Production/Stable
Classifier: Framework :: Django
Classifier: Intended Audience :: Developers
Classifier: License :: OSI Approved :: BSD License
Classifier: Natural Language :: English
Classifier: Framework :: Django
Classifier: Framework :: Django :: 4.2
Classifier: Programming Language :: Python :: 3
Classifier: Programming Language :: Python :: 3.10
Classifier: Programming Language :: Python :: 3.11
Requires-Python: >=3.10
License-File: LICENSE
Requires-Dist: django-cms>=3.11
Provides-Extra: docs
Requires-Dist: django<5.0; extra == "docs"
